abraxos/__init__.py
abraxos/exceptions.py
abraxos/extract.py
abraxos/load.py
abraxos/transform.py
abraxos/utils.py
abraxos/validate.py
docs/conf.py
tests/conftest.py
tests/test_all.py
tests/test_extract.py
tests/test_integration.py
tests/test_load.py
tests/test_read.py
tests/test_transform.py
tests/test_utils.py
tests/test_validate.py
abraxos-0.1.0.dist-info/LICENSE.txt
abraxos-0.1.0.dist-info/METADATA
abraxos-0.1.0.dist-info/WHEEL
abraxos-0.1.0.dist-info/top_level.txt
abraxos-0.1.0.dist-info/RECORD
