Metadata-Version: 2.1
Name: abraxos
Version: 0.1.0
Summary: Upgrade your Pandas ETL process.
Author-email: Odos Matthews <eddiethedean@gmail.com>
License: MIT License
Project-URL: Documentation, https://abraxos.readthedocs.io
Project-URL: Source, https://github.com/eddiethedean/abraxos
Project-URL: Tracker, https://github.com/eddiethedean/abraxos/issues
Keywords: etl,validation,sql,csv,pandas,pydantic
Requires-Python: >=3.10
License-File: LICENSE.txt
Requires-Dist: pandas >=1.5.0
Requires-Dist: numpy >=1.23.0
Provides-Extra: all
Requires-Dist: abraxos[dev,sql,validate] ; extra == 'all'
Provides-Extra: dev
Requires-Dist: pytest >=7.4.0 ; extra == 'dev'
Requires-Dist: pytest-cov >=4.1.0 ; extra == 'dev'
Requires-Dist: mypy >=1.5.0 ; extra == 'dev'
Requires-Dist: ruff >=0.1.0 ; extra == 'dev'
Requires-Dist: pre-commit >=3.4.0 ; extra == 'dev'
Provides-Extra: sql
Requires-Dist: sqlalchemy >=2.0.0 ; extra == 'sql'
Provides-Extra: validate
Requires-Dist: pydantic >=2.0.0 ; extra == 'validate'
